twinlib/__init__.py
twinlib/main.py
twinlib-0.2.2.dist-info/METADATA
twinlib-0.2.2.dist-info/WHEEL
twinlib-0.2.2.dist-info/entry_points.txt
twinlib-0.2.2.dist-info/top_level.txt
twinlib-0.2.2.dist-info/RECORD
