Metadata-Version: 2.1
Name: twinlib
Version: 0.2.2
Summary: A library for twin detection
Author: gaiamzz
Author-email: mzzgai@unife.it
Classifier: Programming Language :: Python :: 3
Classifier: License :: OSI Approved :: MIT License
Classifier: Operating System :: OS Independent
